ares_afr/__init__.py
ares_afr/factorsKZ.csv
ares_afr-3.0.6.dist-info/METADATA
ares_afr-3.0.6.dist-info/WHEEL
ares_afr-3.0.6.dist-info/top_level.txt
ares_afr-3.0.6.dist-info/RECORD
