Metadata-Version: 2.4
Name: ares_afr
Version: 3.0.6
Summary: ARES: Advanced Toolkit for Financial and Non-financial Data Assessment
Author: Aryslan Iskakov
Author-email: iskakov.aryslan@gmail.com
License: BSD-3-Clause
Classifier: Programming Language :: Python :: 3
Classifier: License :: OSI Approved :: BSD License
Classifier: Operating System :: OS Independent
Requires-Python: >=3.6
